steampie/__init__.py
steampie/client.py
steampie/confirmation.py
steampie/exceptions.py
steampie/guard.py
steampie/login.py
steampie/models.py
steampie/utils.py
steampie-0.2.0.dist-info/LICENSE
steampie-0.2.0.dist-info/METADATA
steampie-0.2.0.dist-info/WHEEL
steampie-0.2.0.dist-info/top_level.txt
steampie-0.2.0.dist-info/RECORD
