Metadata-Version: 2.1
Name: steampie
Version: 0.2.0
Summary: Interact with Steam using Python 3
Author-email: offish <overutilization@gmail.com>
Project-URL: Homepage, https://github.com/offish/steampie
Project-URL: Bug Tracker, https://github.com/offish/steampie/issues
Keywords: steam,steampie,steampy,steamio
Classifier: Programming Language :: Python :: 3
Classifier: License :: OSI Approved :: MIT License
Classifier: Operating System :: OS Independent
Requires-Python: >=3.12
License-File: LICENSE
Requires-Dist: rsa
Requires-Dist: beautifulsoup4
Requires-Dist: requests
